MANIFEST.in
README.md
README.rst
dependencies.txt
ffmpeg-audio.sh
ffmpeg-pulse.sh
ffmpeg-sample.sh
setup.cfg
setup.py
docker/Dockerfile
docs/Makefile
docs/conf.py
docs/contributing.rst
docs/history.rst
docs/index.rst
docs/installation.rst
docs/make.bat
docs/readme.rst
docs/usage.rst
recogpipe/__init__.py
recogpipe/daemon.py
recogpipe/dockersetup.py
recogpipe/ibusengine.py
recogpipe.egg-info/PKG-INFO
recogpipe.egg-info/SOURCES.txt
recogpipe.egg-info/dependency_links.txt
recogpipe.egg-info/entry_points.txt
recogpipe.egg-info/not-zip-safe
recogpipe.egg-info/top_level.txt
samples/noisy-test-001.wav
samples/this-is-a-test.wav
tests/__init__.py
tests/test_recogpipe.py